VRCDataImporter/__init__.py
VRCDataImporter/main.py
VRCDataImporter-0.3.dist-info/METADATA
VRCDataImporter-0.3.dist-info/WHEEL
VRCDataImporter-0.3.dist-info/top_level.txt
VRCDataImporter-0.3.dist-info/RECORD
