Metadata-Version: 2.1
Name: VRCDataImporter
Version: 0.3
Requires-Dist: pandas >=2.2.0
